<?xml version="1.0"?>
<gconf>
	<dir name="schemas">
		<dir name="system">
			<dir name="smb">
				<entry name="workgroup">
					<local_schema short_desc="Workgroup SMB">
						<longdesc>Il workgroup o dominio della rete tipo Windows di cui l&apos;utente fa parte. È necessario terminare la sessione e riavviarla per poter operare pienamente dopo aver inserito un nuovo workgroup.</longdesc>
					</local_schema>
				</entry>
			</dir>
			<dir name="proxy">
				<entry name="autoconfig_url">
					<local_schema short_desc="URL di configurazione automatica del proxy">
						<longdesc>URL che fornisce i valori di configurazione del proxy.</longdesc>
					</local_schema>
				</entry>
				<entry name="socks_port">
					<local_schema short_desc="Porta del proxy SOCKS">
						<longdesc>La porta sulla macchina definita in &quot;/system/proxy/socks_host&quot; attraverso la quale effettuare il proxy.</longdesc>
					</local_schema>
				</entry>
				<entry name="socks_host">
					<local_schema short_desc="Nome dell&apos;host proxy SOCKS">
						<longdesc>Il nome della macchina attraverso la quale effettuare il proxy SOCKS.</longdesc>
					</local_schema>
				</entry>
				<entry name="ftp_port">
					<local_schema short_desc="Porta proxy FTP">
						<longdesc>La porta sulla macchina definita in &quot;/system/proxy/ftp_host&quot; attraverso la quale effettuare il proxy.</longdesc>
					</local_schema>
				</entry>
				<entry name="ftp_host">
					<local_schema short_desc="Nome dell&apos;host proxy FTP">
						<longdesc>Il nome della macchina attraverso la quale effettuare il proxy FTP.</longdesc>
					</local_schema>
				</entry>
				<entry name="secure_port">
					<local_schema short_desc="Porta del proxy HTTP sicuro">
						<longdesc>La porta sulla macchina definita in &quot;/system/proxy/secure_host&quot; attraverso la quale effettuare il proxy.</longdesc>
					</local_schema>
				</entry>
				<entry name="secure_host">
					<local_schema short_desc="Nome dell&apos;host proxy HTTP sicuro">
						<longdesc>Il nome della macchina attraverso la quale effettuare il proxy HTTP sicuro.</longdesc>
					</local_schema>
				</entry>
				<entry name="mode">
					<local_schema short_desc="Modalità di configurazione proxy">
						<longdesc>Selezionare la modalità di configurazione del proxy. Valori ammessi sono &quot;none&quot;, &quot;manual&quot;, &quot;auto&quot;.</longdesc>
					</local_schema>
				</entry>
			</dir>
			<dir name="http_proxy">
				<entry name="ignore_hosts">
					<local_schema short_desc="Host non sottoposti a proxy">
						<longdesc>Questa chiave contiene una lista di host a cui connettersi direttamente, invece che attraverso il proxy (qualora sia attivo). Valori ammessi sono nomi degli host, domini (usando un metacarattere iniziale come *.foo.com), indirizzi IP degli host (sia IPv4 che IPv6) ed indirizzi di rete con una maschera di rete (qualcosa come 192.168.0.0/24).</longdesc>
					</local_schema>
				</entry>
				<entry name="authentication_password">
					<local_schema short_desc="Password per proxy HTTP">
						<longdesc>Password da fornire come autenticazione nell&apos;effettuare proxy HTTP.</longdesc>
					</local_schema>
				</entry>
				<entry name="authentication_user">
					<local_schema short_desc="Nome utente per proxy HTTP">
						<longdesc>Nome utente da fornire come autenticazione nell&apos;effettuare proxy HTTP.</longdesc>
					</local_schema>
				</entry>
				<entry name="use_authentication">
					<local_schema short_desc="Autenticazione connessioni al server proxy">
						<longdesc>Se impostata a vero, le connessioni al server proxy richiedono l&apos;autenticazione. La combinazione nome utente/password è definita nelle chiavi &quot;/system/http_proxy/authentication_user&quot; e &quot;/system/http_proxy/authentication_password&quot;.</longdesc>
					</local_schema>
				</entry>
				<entry name="port">
					<local_schema short_desc="Porta proxy HTTP">
						<longdesc>La porta sulla macchina definita in &quot;/system/http_proxy/host&quot; attraverso la quale effettuare il proxy.</longdesc>
					</local_schema>
				</entry>
				<entry name="host">
					<local_schema short_desc="Nome dell&apos;host proxy HTTP">
						<longdesc>Il nome della macchina attraverso la quale effettuare il proxy HTTP.</longdesc>
					</local_schema>
				</entry>
				<entry name="use_http_proxy">
					<local_schema short_desc="Usare proxy HTTP">
						<longdesc>Abilita le impostazioni del proxy per gli accessi HTTP su Internet.</longdesc>
					</local_schema>
				</entry>
			</dir>
			<dir name="dns_sd">
				<entry name="extra_domains">
					<local_schema short_desc="Domini aggiuntivi da interrogare per servizi DNS-SD">
						<longdesc>Elenco separato da virgole di domini DNS-SD che dovrebbero essere visibili nella posizione &quot;network:///&quot;.</longdesc>
					</local_schema>
				</entry>
				<entry name="display_local">
					<local_schema short_desc="Visualizzazione del servizio DNS-SD locale">
						<longdesc>Valori ammessi sono &quot;merged&quot;, &quot;separate&quot; e &quot;disabled&quot;.</longdesc>
					</local_schema>
				</entry>
			</dir>
		</dir>
		<dir name="desktop">
			<dir name="gnome">
				<dir name="typing_break">
					<entry name="enabled">
						<local_schema short_desc="Indica se il blocco della tastiera è attivato">
							<longdesc>Indica se il blocco della tastiera è attivato.</longdesc>
						</local_schema>
					</entry>
					<entry name="allow_postpone">
						<local_schema short_desc="Consenti posposizione delle pause">
							<longdesc>Indica se la schermata di pausa nella scrittura può essere posposta.</longdesc>
						</local_schema>
					</entry>
					<entry name="break_time">
						<local_schema short_desc="Durata pausa">
							<longdesc>Durata in minuti della pausa.</longdesc>
						</local_schema>
					</entry>
					<entry name="type_time">
						<local_schema short_desc="Durata digitazione">
							<longdesc>Numero di minuti di digitazione prima dell&apos;inizio della modalità di pausa</longdesc>
						</local_schema>
					</entry>
				</dir>
				<dir name="thumbnailers">
					<entry name="disable_all">
						<local_schema short_desc="Disabilita tutti i creatori di miniature esterni">
							<longdesc>Impostare a vero per disabilitare tutti i programmi esterni per creare provini e miniature, indipendentemente dalle impostazioni di ciascuno di essi.</longdesc>
						</local_schema>
					</entry>
				</dir>
				<dir name="thumbnail_cache">
					<entry name="maximum_size">
						<local_schema>
							<longdesc>Dimensione massima della cache delle miniature, in megabyte. Impostare a -1 per disabilitare la pulizia.</longdesc>
						</local_schema>
					</entry>
					<entry name="maximum_age">
						<local_schema>
							<longdesc>Età massima per le miniature nella cache, in giorni. Impostare a -1 per disabilitare la pulizia.</longdesc>
						</local_schema>
					</entry>
				</dir>
				<dir name="sound">
					<entry name="input_feedback_sounds">
						<local_schema short_desc="Suoni di riscontro dell&apos;input">
							<longdesc>Indica se usare suoni quando avvengono eventi di input.</longdesc>
						</local_schema>
					</entry>
					<entry name="theme_name">
						<local_schema short_desc="Nome del tema sonoro">
							<longdesc>Il tema sonoro XDG da usare per i suoni degli eventi.</longdesc>
						</local_schema>
					</entry>
					<entry name="event_sounds">
						<local_schema short_desc="Suoni per eventi">
							<longdesc>Indica se usare suoni quando avvengono eventi utente.</longdesc>
						</local_schema>
					</entry>
					<entry name="enable_esd">
						<local_schema short_desc="Abilita ESD">
							<longdesc>Abilita il server sonoro all&apos;avvio.</longdesc>
						</local_schema>
					</entry>
					<entry name="default_mixer_tracks">
						<local_schema short_desc="Tracce mixer predefinite">
							<longdesc>Le tracce del mixer predefinito usato dalle associazioni dei tasti multimediali.</longdesc>
						</local_schema>
					</entry>
					<entry name="default_mixer_device">
						<local_schema short_desc="Device mixer predefinito">
							<longdesc>Il device del mixer predefinito usato dalle associazioni dei tasti multimediali.</longdesc>
						</local_schema>
					</entry>
				</dir>
				<dir name="peripherals">
					<dir name="mouse">
						<entry name="cursor_size">
							<local_schema short_desc="Dimensione del cursore">
								<longdesc>Dimensione del cursore indicato da cursor_theme.</longdesc>
							</local_schema>
						</entry>
						<entry name="cursor_theme">
							<local_schema short_desc="Tema del cursore">
								<longdesc>Nome del tema del cursore. Usato solo dagli Xserver che supportano Xcursor, come XFree86 4.3 e oltre.</longdesc>
							</local_schema>
						</entry>
						<entry name="cursor_font">
							<local_schema short_desc="Carattere del cursore">
								<longdesc>Nome del tipo carattere del cursore. Se non impostato, sarà usato il carattere predefinito. Questo valore è inviato al server X solo all&apos;inizio di ogni sessione, per cui cambiandolo durante una sessione non si avrà alcun effetto fino al successivo accesso.</longdesc>
							</local_schema>
						</entry>
						<entry name="locate_pointer">
							<local_schema short_desc="Localizza puntatore">
								<longdesc>Evidenzia la posizione attuale del puntatore quando il tasto Control è premuto e rilasciato.</longdesc>
							</local_schema>
						</entry>
						<entry name="double_click">
							<local_schema short_desc="Tempo del doppio clic">
								<longdesc>Durata di un doppio clic.</longdesc>
							</local_schema>
						</entry>
						<entry name="drag_threshold">
							<local_schema short_desc="Soglia trascinamento">
								<longdesc>Distanza prima di avviare un trascinamento.</longdesc>
							</local_schema>
						</entry>
						<entry name="motion_threshold">
							<local_schema short_desc="Soglia movimento">
								<longdesc>Numero di pixel di cui muovere il puntatore prima che il movimento accelerato del mouse sia attivato. Impostare a -1 per usare le preferenze di sistema.</longdesc>
							</local_schema>
						</entry>
						<entry name="motion_acceleration">
							<local_schema short_desc="Singolo clic">
								<longdesc>Moltiplicatore dell&apos;accelerazione per il movimento del mouse. Impostare a -1 per usare le preferenze di sistema.</longdesc>
							</local_schema>
						</entry>
						<entry name="single_click">
							<local_schema short_desc="Singolo clic">
								<longdesc>Singolo clic per aprire le icone.</longdesc>
							</local_schema>
						</entry>
						<entry name="left_handed">
							<local_schema short_desc="Orientazione tasti del mouse">
								<longdesc>Inverte i tasti destro e sinistro del mouse per mancini.</longdesc>
							</local_schema>
						</entry>
					</dir>
					<dir name="keyboard">
						<entry name="remember_numlock_state">
							<local_schema short_desc="Ricorda lo stato di BlocNum">
								<longdesc>Quando impostato a &quot;true&quot;, GNOME ricorderà lo stato del LED BlocNum da una sessione all&apos;altra.</longdesc>
							</local_schema>
						</entry>
						<entry name="bell_custom_file">
							<local_schema short_desc="Nome del file personalizzato della campanella da tastiera">
								<longdesc>Nome del file del suono della campanella da riprodurre.</longdesc>
							</local_schema>
						</entry>
						<entry name="bell_mode">
							<local_schema>
								<longdesc>Valori ammessi sono &quot;on&quot; &quot;off&quot; e &quot;custom&quot;.</longdesc>
							</local_schema>
						</entry>
					</dir>
				</dir>
				<dir name="lockdown">
					<entry name="disable_application_handlers">
						<local_schema short_desc="Disabilitare i gestori degli URL e dei tipi MIME">
							<longdesc>Impedisce l&apos;esecuzione di qualsiasi applicazione di gestione URL o tipo MIME.</longdesc>
						</local_schema>
					</entry>
					<entry name="disable_lock_screen">
						<local_schema short_desc="Disabilita blocco schermo">
							<longdesc>Impedisce all&apos;utente di bloccare lo schermo.</longdesc>
						</local_schema>
					</entry>
					<entry name="disable_user_switching">
						<local_schema short_desc="Disabilita cambio utente">
							<longdesc>Impedisce all&apos;utente di passare a un altro account fin quando la sua sessione è attiva.</longdesc>
						</local_schema>
					</entry>
					<entry name="disable_print_setup">
						<local_schema short_desc="Disabilita impostazione stampa">
							<longdesc>Impedisce all&apos;utente di modificare le impostazioni di stampa. Per esempio questo disabiliterebbe l&apos;accesso alle finestre di dialogo &quot;Imposta stampa&quot; di tutte le applicazioni.</longdesc>
						</local_schema>
					</entry>
					<entry name="disable_printing">
						<local_schema short_desc="Disabilita stampa">
							<longdesc>Impedisce all&apos;utente di stampare. Per esempio questo disabiliterebbe l&apos;accesso alle finestre di dialogo &quot;Stampa&quot; di tutte le applicazioni.</longdesc>
						</local_schema>
					</entry>
					<entry name="disable_save_to_disk">
						<local_schema short_desc="Disabilita salvataggio file su disco">
							<longdesc>Impedisce all&apos;utente di salvare i file su disco. Per esempio questo disabiliterebbe l&apos;accesso alle finestre di dialogo &quot;Salva come&quot; di tutte le applicazioni.</longdesc>
						</local_schema>
					</entry>
					<entry name="disable_command_line">
						<local_schema short_desc="Disabilita riga di comando">
							<longdesc>Impedisce all&apos;utente di accedere al terminale o di specificare una riga di comando da eseguire. Per esempio, questo disabiliterebbe l&apos;accesso alla finestra di dialogo &quot;Esegui applicazione&quot; del pannello.</longdesc>
						</local_schema>
					</entry>
				</dir>
				<dir name="interface">
					<entry name="show_unicode_menu">
						<local_schema short_desc="Mostra il menù &quot;Caratteri di controllo Unicode&quot;">
							<longdesc>Indica se i menù contestuali dei campi e delle viste di testo possono offrire di inserire caratteri di controllo.</longdesc>
						</local_schema>
					</entry>
					<entry name="show_input_method_menu">
						<local_schema short_desc="Mostra il menù &quot;Metodi di input&quot;">
							<longdesc>Indica se i menù contestuali dei campi e delle viste di testo possono offrire di cambiare il metodo di input.</longdesc>
						</local_schema>
					</entry>
					<entry name="menubar_accel">
						<local_schema short_desc="Acceleratore della barra dei menù">
							<longdesc>Scorciatoia da tastiera per aprire le barre dei menù.</longdesc>
						</local_schema>
					</entry>
					<entry name="file_chooser_backend">
						<local_schema short_desc="Modulo per GtkFileChooser">
							<longdesc>Modulo da usare come modello di filesystem per il widget GtkFileChooser. 
I valori possibili sono &quot;gio&quot;, &quot;gnome-vfs&quot; e &quot;gtk+&quot;.</longdesc>
						</local_schema>
					</entry>
					<entry name="status_bar_meter_on_right">
						<local_schema short_desc="Barra di stato a destra">
							<longdesc>Indica se porre a destra l&apos;indicatore sulla barra di stato.</longdesc>
						</local_schema>
					</entry>
					<entry name="use_custom_font">
						<local_schema short_desc="Usa carattere personalizzato">
							<longdesc>Indica se usare un tipo di carattere personalizzato nelle applicazioni GTK+.</longdesc>
						</local_schema>
					</entry>
					<entry name="monospace_font_name">
						<local_schema short_desc="Carattere monospace">
							<longdesc>Il nome di un carattere monospace (a larghezza fissa) da usare in posizioni come i terminali.</longdesc>
						</local_schema>
					</entry>
					<entry name="document_font_name">
						<local_schema short_desc="Tipo di carattere per i documenti">
							<longdesc>Nome del tipo di carattere usato in modo predefinito per leggere i documenti.</longdesc>
						</local_schema>
					</entry>
					<entry name="gtk-im-module">
						<local_schema short_desc="Modulo IM GTK+">
							<longdesc>Nome del modulo del metodo di input usato dalle GTK+.</longdesc>
						</local_schema>
					</entry>
					<entry name="gtk-im-status-style">
						<local_schema short_desc="Stile GTK+ IM Status">
							<longdesc>Nome del metodo di input delle GTK+ Status Style usato.</longdesc>
						</local_schema>
					</entry>
					<entry name="gtk-im-preedit-style">
						<local_schema short_desc="Stile GTK+ IM Preedit">
							<longdesc>Nome del metodo di input delle GTK+ Preedit Style usato.</longdesc>
						</local_schema>
					</entry>
					<entry name="font_name">
						<local_schema short_desc="Tipo di carattere predefinito">
							<longdesc>Nome del tipo di carattere usato in modo predefinito dalle GTK+.</longdesc>
						</local_schema>
					</entry>
					<entry name="gtk_key_theme">
						<local_schema short_desc="Tema GTK+">
							<longdesc>Nome di base del tema predefinito usato dalle GTK+.</longdesc>
						</local_schema>
					</entry>
					<entry name="gtk_theme">
						<local_schema short_desc="Tema GTK+">
							<longdesc>Nome di base del tema predefinito usato dalle GTK+.</longdesc>
						</local_schema>
					</entry>
					<entry name="icon_theme">
						<local_schema short_desc="Tema delle icone">
							<longdesc>Tema delle icone usato per il pannello, nautilus, ecc.</longdesc>
						</local_schema>
					</entry>
					<entry name="cursor_blink_time">
						<local_schema short_desc="Intervallo di lampeggiamento cursore">
							<longdesc>Durata del ciclo di lampeggiamento del cursore, in millisecondi.</longdesc>
						</local_schema>
					</entry>
					<entry name="cursor_blink">
						<local_schema short_desc="Cursore lampeggiante">
							<longdesc>Indica se il cursore debba lampeggiare.</longdesc>
						</local_schema>
					</entry>
					<entry name="toolbar_icons_size">
						<local_schema short_desc="Dimensione delle icone della barra strumenti">
							<longdesc>Dimensione delle icone nella barra degli strumenti, a scelta tra &quot;small-toolbar&quot; o &quot;large-toolbar&quot;.</longdesc>
						</local_schema>
					</entry>
					<entry name="toolbar_detachable">
						<local_schema short_desc="Barra degli strumenti staccabile">
							<longdesc>Indica se l&apos;utente può staccare le barre degli strumenti e spostarle.</longdesc>
						</local_schema>
					</entry>
					<entry name="menubar_detachable">
						<local_schema short_desc="Barra dei menù staccabile">
							<longdesc>Indica se l&apos;utente può staccare le barre dei menù e spostarle.</longdesc>
						</local_schema>
					</entry>
					<entry name="buttons_have_icons">
						<local_schema short_desc="Pulsanti con icone">
							<longdesc>Indica se i pulsanti devono visualizzare un&apos;icona oltre al testo.</longdesc>
						</local_schema>
					</entry>
					<entry name="menus_have_icons">
						<local_schema short_desc="Menù con icone">
							<longdesc>Indica se debba essere mostrata un&apos;icona accanto alle voci di menù.</longdesc>
						</local_schema>
					</entry>
					<entry name="toolbar_style">
						<local_schema short_desc="Stile della barra strumenti">
							<longdesc>Stile della barra degli strumenti. Valori ammessi sono: &quot;both&quot;, &quot;both-horiz&quot;, &quot;icons&quot; e &quot;text&quot;.</longdesc>
						</local_schema>
					</entry>
					<entry name="can_change_accels">
						<local_schema short_desc="Consenti cambio acceleratori">
							<longdesc>Indica se l&apos;utente può digitare dinamicamente un nuovo acceleratore quando è posizionato sopra una voce di menù attiva.</longdesc>
						</local_schema>
					</entry>
					<entry name="menus_have_tearoff">
						<local_schema short_desc="Menù con staccatore">
							<longdesc>Indica se i menù debbano avere uno staccatore.</longdesc>
						</local_schema>
					</entry>
					<entry name="enable_animations">
						<local_schema short_desc="Abilita animazioni">
							<longdesc>Indica se si debbano visualizzare le animazioni. Attenzione: questa è una chiave globale, permette di cambiare il comportamento del window manager, del pannello, etc.</longdesc>
						</local_schema>
					</entry>
					<entry name="accessibility">
						<local_schema short_desc="Abilita accessibilità">
							<longdesc>Indica se le applicazioni debbano avere il supporto per l&apos;accessibilità.</longdesc>
						</local_schema>
					</entry>
				</dir>
				<dir name="file-views">
					<entry name="icon_theme">
						<local_schema short_desc="Tema icone dei file">
							<longdesc>Tema usato per visualizzare le icone dei file.</longdesc>
						</local_schema>
					</entry>
				</dir>
				<dir name="background">
					<entry name="color_shading_type">
						<local_schema short_desc="Tipo sfumatura colore">
							<longdesc>Indica come sfumare il colore di sfondo. Valori ammessi sono &quot;horizontal-gradient&quot;, &quot;vertical-gradient&quot; e &quot;solid&quot;.</longdesc>
						</local_schema>
					</entry>
					<entry name="secondary_color">
						<local_schema short_desc="Colore secondario">
							<longdesc>Colore a destra o in basso quando si disegna un gradiente, non usato per la tinta unita.</longdesc>
						</local_schema>
					</entry>
					<entry name="primary_color">
						<local_schema short_desc="Colore primario">
							<longdesc>Colore in alto o a sinistra quando si utilizza un gradiente, oppure il colore per la tinta unita.</longdesc>
						</local_schema>
					</entry>
					<entry name="picture_opacity">
						<local_schema short_desc="Opacità immagine">
							<longdesc>Opacità con cui disegnare l&apos;immagine di sfondo.</longdesc>
						</local_schema>
					</entry>
					<entry name="picture_filename">
						<local_schema short_desc="Nome del file di immagine">
							<longdesc>File da usare come immagine di sfondo.</longdesc>
						</local_schema>
					</entry>
					<entry name="picture_options">
						<local_schema short_desc="Opzioni immagine">
							<longdesc>Determina come è gestita l&apos;immagine impostata in &quot;wallpaper_filename&quot;. Valori ammessi sono: &quot;none&quot;, &quot;wallpaper&quot;, &quot;centered&quot;, &quot;scaled&quot;, &quot;stretched&quot;, &quot;zoom&quot; e &quot;spanned&quot;.</longdesc>
						</local_schema>
					</entry>
					<entry name="draw_background">
						<local_schema short_desc="Disegna sfondo scrivania">
							<longdesc>Indica se GNOME debba disegnare lo sfondo della scrivania.</longdesc>
						</local_schema>
					</entry>
				</dir>
				<dir name="applications">
					<dir name="component_viewer">
						<entry name="exec">
							<local_schema short_desc="Applicazione di visualizzatore componente predefinita">
								<longdesc>L&apos;applicazione da usare per visualizzare i file che richiedono un componente per essere visualizzati. Il parametro %s viene sostituito con l&apos;URI del file, il parametro %c viene sostituito con l&apos;IID del componente.</longdesc>
							</local_schema>
						</entry>
					</dir>
					<dir name="window_manager">
						<entry name="workspace_names">
							<local_schema short_desc="Nomi delle aree di lavoro (deprecata)">
								<longdesc>Una lista con i nomi delle aree di lavoro del window manager primario. Questa chiave è stata resa deprecata a partire da GNOME 2.12.</longdesc>
							</local_schema>
						</entry>
						<entry name="number_of_workspaces">
							<local_schema short_desc="Il numero delle aree di lavoro (deprecata)">
								<longdesc>Il numero delle aree di lavoro che il window manager dovrebbe usare. Questa chiave è stata resa deprecata a partire da GNOME 2.12.</longdesc>
							</local_schema>
						</entry>
						<entry name="current">
							<local_schema short_desc="Window manager dell&apos;utente (deprecata)">
								<longdesc>Window manager da provare per primo. Questa chiave è stata resa deprecata a partire da GNOME 2.12.</longdesc>
							</local_schema>
						</entry>
						<entry name="default">
							<local_schema short_desc="Window manager di ripiego (deprecata)">
								<longdesc>Window manager da usare come ripiego se quello scelto dall&apos;utente non viene trovato. Questa chiave è stata resa deprecata a partire da GNOME 2.12.</longdesc>
							</local_schema>
						</entry>
					</dir>
					<dir name="terminal">
						<entry name="exec_arg">
							<local_schema short_desc="Argomento exec per il terminale predefinito">
								<longdesc>L&apos;argomento exec da usare per l&apos;applicazione di terminale predefinita.</longdesc>
							</local_schema>
						</entry>
						<entry name="exec">
							<local_schema short_desc="Applicazione di terminale predefinita">
								<longdesc>Applicazione di terminale predefinita da usare per applicazioni che richiedono un terminale.</longdesc>
							</local_schema>
						</entry>
					</dir>
					<dir name="tasks">
						<entry name="needs_term">
							<local_schema short_desc="Compiti necessita del terminale">
								<longdesc>Indica se l&apos;applicazione per i compiti predefinita necessita di un terminale per essere eseguita</longdesc>
							</local_schema>
						</entry>
						<entry name="exec">
							<local_schema short_desc="Compiti predefinito">
								<longdesc>Applicazione di compiti predefinita</longdesc>
							</local_schema>
						</entry>
					</dir>
					<dir name="calendar">
						<entry name="needs_term">
							<local_schema short_desc="Calendario necessita del terminale">
								<longdesc>Indica se l&apos;applicazione calendario predefinita necessita di un terminale per essere eseguita</longdesc>
							</local_schema>
						</entry>
						<entry name="exec">
							<local_schema short_desc="Calendario predefinito">
								<longdesc>Applicazione di calendario predefinita</longdesc>
							</local_schema>
						</entry>
					</dir>
					<dir name="browser">
						<entry name="nremote">
							<local_schema short_desc="Il browser gestisce file remoti">
								<longdesc>Indica se il browser predefinito gestisce l&apos;opzione &apos;remote&apos; di Netscape.</longdesc>
							</local_schema>
						</entry>
						<entry name="needs_term">
							<local_schema short_desc="Il browser necessita del terminale">
								<longdesc>Indica se il browser predefinito necessita di un terminale per essere eseguito.</longdesc>
							</local_schema>
						</entry>
						<entry name="exec">
							<local_schema short_desc="Browser predefinito">
								<longdesc>Browser predefinito per ogni URL.</longdesc>
							</local_schema>
						</entry>
					</dir>
					<dir name="at">
						<dir name="visual">
							<entry name="startup">
								<local_schema short_desc="Avvio applicazione di tecnologia assistiva per disabilità visive preferita">
									<longdesc>GNONE avvierà l&apos;applicazione di tecnologia assistiva per disabilità visive predefinita durante l&apos;accesso.</longdesc>
								</local_schema>
							</entry>
							<entry name="exec">
								<local_schema short_desc="Applicazione di tecnologia assistiva per disabilità visive preferita">
									<longdesc>Applicazione preferita di tecnologia assistiva per disabilità visive preferita da usare per l&apos;accesso, i menù o la riga di comando.</longdesc>
								</local_schema>
							</entry>
						</dir>
						<dir name="mobility">
							<entry name="startup">
								<local_schema short_desc="Avvio applicazione di tecnologia assistiva per disabilità motorie preferita">
									<longdesc>GNOME avvierà l&apos;applicazione di tecnologia assistiva per disabilità motorie durante l&apos;accesso.</longdesc>
								</local_schema>
							</entry>
							<entry name="exec">
								<local_schema short_desc="Applicazione di tecnologia assistiva per disabilità motorie.">
									<longdesc>Applicazione preferita di tecnologia assistiva per disabilità motorie da usare per l&apos;accesso, i menù o la riga di comando.</longdesc>
								</local_schema>
							</entry>
						</dir>
					</dir>
				</dir>
				<dir name="accessibility">
					<dir name="startup">
						<entry name="exec_ats">
							<local_schema short_desc="Avvio applicazioni tecnologia assistiva">
								<longdesc>Elenco delle applicazioni di tecnologia assistiva da avviare quando si accede nell&apos;ambiente grafico GNOME.</longdesc>
							</local_schema>
						</entry>
					</dir>
					<dir name="keyboard">
						<entry name="stickykeys_modifier_beep">
							<local_schema>
								<longdesc>Segnale acustico alla pressione di un modificatore.</longdesc>
							</local_schema>
						</entry>
						<entry name="stickykeys_two_key_off">
							<local_schema>
								<longdesc>Disabilita se due tasti sono premuti contemporaneamente.</longdesc>
							</local_schema>
						</entry>
						<entry name="slowkeys_delay">
							<local_schema short_desc="Intervallo minimo in millisecondi">
								<longdesc>Non accetta un tasto se non è stato mantenuto premuto per almeno @delay millisecondi.</longdesc>
							</local_schema>
						</entry>
						<entry name="mousekeys_init_delay">
							<local_schema short_desc="Ritardo iniziale in millisecondi">
								<longdesc>Quanti millisecondi attendere prima che i tasti per il movimento del mouse inizino a operare.</longdesc>
							</local_schema>
						</entry>
						<entry name="mousekeys_accel_time">
							<local_schema short_desc="Durata dell&apos;accelerazione in millisecondi">
								<longdesc>Quanti millisecondi sono necessari per andare da 0 alla velocità massima.</longdesc>
							</local_schema>
						</entry>
						<entry name="mousekeys_max_speed">
							<local_schema short_desc="Pixel al secondo">
								<longdesc>Di quanti pixel al secondo muovere alla massima velocità.</longdesc>
							</local_schema>
						</entry>
						<entry name="bouncekeys_delay">
							<local_schema short_desc="Intervallo minimo in millisecondi">
								<longdesc>Ignora pressioni multiple dello STESSO tasto se entro @delay millisecondi.</longdesc>
							</local_schema>
						</entry>
					</dir>
				</dir>
			</dir>
		</dir>
	</dir>
</gconf>
